{
    "level_number": 7,
    "grid_width": 9,
    "grid_height": 10,
    "move_count": 65,
    "pattern": "square",
    "grid": [
        "bo",
        "bo",
        "bo",
        "bo",
        "bo",
        "bo",
        "bo",
        "bo",
        "bo",
        "bo",
        "rand",
        "rand",
        "rand",
        "rand",
        "rand",
        "rand",
        "rand",
        "bo",
        "bo",
        "rand",
        "v",
        "rand",
        "s",
        "rand",
        "v",
        "rand",
        "bo",
        "bo",
        "rand",
        "rand",
        "g",
        "b",
        "y",
        "rand",
        "rand",
        "bo",
        "bo",
        "rand",
        "s",
        "b",
        "em",
        "r",
        "s",
        "rand",
        "bo",
        "bo",
        "rand",
        "rand",
        "y",
        "g",
        "b",
        "rand",
        "rand",
        "bo",
        "bo",
        "rand",
        "v",
        "rand",
        "s",
        "rand",
        "v",
        "rand",
        "bo",
        "bo",
        "rand",
        "rand",
        "rand",
        "rand",
        "rand",
        "rand",
        "rand",
        "bo",
        "bo",
        "bo",
        "bo",
        "bo",
        "bo",
        "bo",
        "bo",
        "bo",
        "bo",
        "rand",
        "rand",
        "rand",
        "rand",
        "rand",
        "rand",
        "rand",
        "rand",
        "rand"
    ]
}
